batchcrop/__init__.py
batchcrop/cli/__init__.py
batchcrop/cli/batchcrop.py
batchcrop-0.1.1.dist-info/LICENSE
batchcrop-0.1.1.dist-info/METADATA
batchcrop-0.1.1.dist-info/WHEEL
batchcrop-0.1.1.dist-info/entry_points.txt
batchcrop-0.1.1.dist-info/top_level.txt
batchcrop-0.1.1.dist-info/RECORD
