Metadata-Version: 2.1
Name: batchcrop
Version: 0.1.1
Summary: Crop a batch of images.
Home-page: https://github.com/tdegeus/batchcrop
Author: Tom de Geus
Author-email: tom@geus.me
License: MIT
Keywords: convert
Platform: UNKNOWN
Requires-Dist: docopt (>=0.6.2)
